alanube/__init__.py
alanube/utils.py
alanube/assets/README.md
alanube/do/__init__.py
alanube/do/api.py
alanube/do/config.py
alanube/do/exceptions.py
alanube/do/types.py
alanube/do/utils.py
alanube/do/validators.py
alanube/tests/__init__.py
alanube/tests/test_do.py
alanube-1.2.0.dist-info/licenses/LICENSE
alanube-1.2.0.dist-info/METADATA
alanube-1.2.0.dist-info/WHEEL
alanube-1.2.0.dist-info/top_level.txt
alanube-1.2.0.dist-info/RECORD
