Metadata-Version: 2.4
Name: alanube
Version: 1.2.0
Summary: Python library to connect with Alanube API
Author: Wilmer Martinez
License-Expression: MIT
Project-URL: Homepage, https://github.com/wilmerm/alanube-python
Project-URL: Issues, https://github.com/wilmerm/alanube-python/issues
Project-URL: Repository, https://github.com/wilmerm/alanube-python
Project-URL: Documentation, https://wilmerm.github.io/alanube-python
Keywords: alanube,api,dgii,ncf,ncf-e,electronic billing,electronic bill,billing,bill,invoice,facturación electrónica,factura,factura electrónica,rd,republica dominicana,dominican republic
Classifier: Development Status :: 5 - Production/Stable
Classifier: Intended Audience :: Developers
Classifier: Topic :: Software Development :: Libraries :: Python Modules
Classifier: Environment :: Web Environment
Classifier: Natural Language :: English
Classifier: Natural Language :: Spanish
Classifier: Programming Language :: Python
Classifier: Programming Language :: Python :: 3.10
Classifier: Programming Language :: Python :: 3.11
Classifier: Programming Language :: Python :: 3.12
Classifier: Programming Language :: Python :: 3.13
Classifier: Programming Language :: Python :: 3.14
Requires-Python: >=3.10
License-File: LICENSE
Requires-Dist: requests
Dynamic: license-file
